createproject/__init__.py
createproject/main.py
createproject/templates/__init__.py
flask_createproject-0.0.4.dist-info/LICENSE
flask_createproject-0.0.4.dist-info/METADATA
flask_createproject-0.0.4.dist-info/WHEEL
flask_createproject-0.0.4.dist-info/entry_points.txt
flask_createproject-0.0.4.dist-info/top_level.txt
flask_createproject-0.0.4.dist-info/RECORD
