Metadata-Version: 2.1
Name: flask-createproject
Version: 0.0.4
Summary: A utility program to bootstrap flask projects
Author: Mohamed Daif
Author-email: daif.control@gmail.com
Classifier: Programming Language :: Python :: 3
Classifier: License :: OSI Approved :: MIT License
Classifier: Operating System :: OS Independent
Requires-Python: >=3.9
License-File: LICENSE
Requires-Dist: Jinja2 (>=3.1.2)
Requires-Dist: colored (>=1.4.3)
Requires-Dist: emoji (>=1.7.0)
